bow_mnb/__init__.py
bow_mnb/mnb.py
bow_mnb-0.0.1.dist-info/LICENSE
bow_mnb-0.0.1.dist-info/METADATA
bow_mnb-0.0.1.dist-info/WHEEL
bow_mnb-0.0.1.dist-info/top_level.txt
bow_mnb-0.0.1.dist-info/RECORD
